{
    "schema":{
        "fields":[
            {
                "name":"Id",
                "type":"string"
            },
            {
                "name":"Nom",
                "type":"string"
            },
            {
                "name":"\u00c9quipe",
                "type":"string"
            },
            {
                "name":"Abbr\u00e9viation",
                "type":"string"
            },
            {
                "name":"PJ",
                "type":"integer"
            },
            {
                "name":"B",
                "type":"integer"
            },
            {
                "name":"A",
                "type":"integer"
            },
            {
                "name":"Score",
                "type":"integer"
            },
            {
                "name":"MasseSalariale",
                "type":"integer"
            }
        ],
        "pandas_version":"0.20.0"
    },
    "data":[
        {
            "Id":"gab",
            "Nom":"Gabriel",
            "\u00c9quipe":"Tropics",
            "Abbr\u00e9viation":"TRO",
            "PJ":428,
            "B":144,
            "A":205,
            "Score":371,
            "MasseSalariale":62914999
        },
        {
            "Id":"cle",
            "Nom":"Cl\u00e9ment",
            "\u00c9quipe":"Rocket",
            "Abbr\u00e9viation":"ROC",
            "PJ":406,
            "B":135,
            "A":218,
            "Score":363,
            "MasseSalariale":75364867
        },
        {
            "Id":"hub",
            "Nom":"Hubert",
            "\u00c9quipe":"Patriotes",
            "Abbr\u00e9viation":"PAT",
            "PJ":378,
            "B":86,
            "A":176,
            "Score":268,
            "MasseSalariale":70815334
        },
        {
            "Id":"rap",
            "Nom":"Rapha\u00ebl",
            "\u00c9quipe":"Storm Surge",
            "Abbr\u00e9viation":"SS",
            "PJ":410,
            "B":123,
            "A":228,
            "Score":368,
            "MasseSalariale":73092857
        }
    ]
}