{
    "schema":{
        "fields":[
            {
                "name":"id",
                "type":"string"
            },
            {
                "name":"nom",
                "type":"string"
            },
            {
                "name":"equipe",
                "type":"string"
            },
            {
                "name":"abbr",
                "type":"string"
            },
            {
                "name":"pj",
                "type":"integer"
            },
            {
                "name":"b",
                "type":"integer"
            },
            {
                "name":"a",
                "type":"integer"
            },
            {
                "name":"score",
                "type":"integer"
            },
            {
                "name":"massesalariale",
                "type":"integer"
            }
        ],
        "pandas_version":"1.4.0"
    },
    "data":[
        {
            "id":"TRO",
            "nom":"Gabriel",
            "equipe":"Tropics",
            "abbr":"gab",
            "pj":984,
            "b":312,
            "a":574,
            "score":907,
            "massesalariale":88103750
        },
        {
            "id":"PAT",
            "nom":"Hubert",
            "equipe":"Patriotes",
            "abbr":"hub",
            "pj":1018,
            "b":307,
            "a":654,
            "score":976,
            "massesalariale":88795095
        },
        {
            "id":"SS",
            "nom":"Rapha\u00ebl",
            "equipe":"Storm Surge",
            "abbr":"rap",
            "pj":936,
            "b":302,
            "a":403,
            "score":756,
            "massesalariale":88216388
        },
        {
            "id":"SLA",
            "nom":"Olivier",
            "equipe":"Slafgoalsky",
            "abbr":"oli",
            "pj":1028,
            "b":272,
            "a":414,
            "score":702,
            "massesalariale":71280000
        },
        {
            "id":"QUA",
            "nom":"J\u00e9r\u00e9mieD",
            "equipe":"Qualis",
            "abbr":"jed",
            "pj":862,
            "b":227,
            "a":341,
            "score":585,
            "massesalariale":92840457
        },
        {
            "id":"NOR",
            "nom":"F\u00e9lix-Antoine",
            "equipe":"Nordiques",
            "abbr":"fab",
            "pj":1148,
            "b":361,
            "a":550,
            "score":959,
            "massesalariale":102384166
        },
        {
            "id":"VOY",
            "nom":"Nicholas",
            "equipe":"Voyageurs",
            "abbr":"nic",
            "pj":978,
            "b":296,
            "a":464,
            "score":777,
            "massesalariale":86782440
        },
        {
            "id":"JOC",
            "nom":"Lo\u00efc",
            "equipe":"Jockstraps",
            "abbr":"loi",
            "pj":840,
            "b":215,
            "a":273,
            "score":490,
            "massesalariale":81963096
        },
        {
            "id":"TWG",
            "nom":"Dannick",
            "equipe":"Wild Generals",
            "abbr":"dan",
            "pj":858,
            "b":246,
            "a":360,
            "score":628,
            "massesalariale":93761667
        },
        {
            "id":"ROC",
            "nom":"Alexandre",
            "equipe":"Rocket",
            "abbr":"ale",
            "pj":1147,
            "b":364,
            "a":499,
            "score":892,
            "massesalariale":93067857
        }
    ]
}