{
    "schema":{
        "fields":[
            {
                "name":"id",
                "type":"string"
            },
            {
                "name":"nom",
                "type":"string"
            },
            {
                "name":"equipe",
                "type":"string"
            },
            {
                "name":"abbr",
                "type":"string"
            },
            {
                "name":"pj",
                "type":"integer"
            },
            {
                "name":"b",
                "type":"integer"
            },
            {
                "name":"a",
                "type":"integer"
            },
            {
                "name":"score",
                "type":"integer"
            },
            {
                "name":"massesalariale",
                "type":"integer"
            }
        ],
        "pandas_version":"1.4.0"
    },
    "data":[
        {
            "id":"TRO",
            "nom":"Gabriel",
            "equipe":"Tropics",
            "abbr":"gab",
            "pj":164,
            "b":59,
            "a":101,
            "score":164,
            "massesalariale":88103750
        },
        {
            "id":"PAT",
            "nom":"Hubert",
            "equipe":"Patriotes",
            "abbr":"hub",
            "pj":174,
            "b":44,
            "a":99,
            "score":145,
            "massesalariale":79545095
        },
        {
            "id":"SS",
            "nom":"Rapha\u00ebl",
            "equipe":"Storm Surge",
            "abbr":"rap",
            "pj":160,
            "b":61,
            "a":77,
            "score":146,
            "massesalariale":88216388
        },
        {
            "id":"SLA",
            "nom":"Olivier",
            "equipe":"Slafgoalsky",
            "abbr":"oli",
            "pj":163,
            "b":44,
            "a":76,
            "score":122,
            "massesalariale":84530000
        },
        {
            "id":"QUA",
            "nom":"J\u00e9r\u00e9mieD",
            "equipe":"Qualis",
            "abbr":"jed",
            "pj":142,
            "b":39,
            "a":58,
            "score":100,
            "massesalariale":92840457
        },
        {
            "id":"NOR",
            "nom":"F\u00e9lix-Antoine",
            "equipe":"Nordiques",
            "abbr":"fab",
            "pj":198,
            "b":61,
            "a":103,
            "score":170,
            "massesalariale":102384166
        },
        {
            "id":"VOY",
            "nom":"Nicholas",
            "equipe":"Voyageurs",
            "abbr":"nic",
            "pj":156,
            "b":50,
            "a":70,
            "score":124,
            "massesalariale":86782440
        },
        {
            "id":"JOC",
            "nom":"Lo\u00efc",
            "equipe":"Jockstraps",
            "abbr":"loi",
            "pj":170,
            "b":55,
            "a":77,
            "score":136,
            "massesalariale":84238096
        },
        {
            "id":"TWG",
            "nom":"Dannick",
            "equipe":"Wild Generals",
            "abbr":"dan",
            "pj":154,
            "b":33,
            "a":63,
            "score":97,
            "massesalariale":93761667
        },
        {
            "id":"ROC",
            "nom":"Alexandre",
            "equipe":"Rocket",
            "abbr":"ale",
            "pj":178,
            "b":64,
            "a":77,
            "score":144,
            "massesalariale":95567857
        }
    ]
}