{
    "schema":{
        "fields":[
            {
                "name":"id",
                "type":"string"
            },
            {
                "name":"nom",
                "type":"string"
            },
            {
                "name":"equipe",
                "type":"string"
            },
            {
                "name":"abbr",
                "type":"string"
            },
            {
                "name":"pj",
                "type":"integer"
            },
            {
                "name":"b",
                "type":"integer"
            },
            {
                "name":"a",
                "type":"integer"
            },
            {
                "name":"score",
                "type":"integer"
            },
            {
                "name":"massesalariale",
                "type":"integer"
            }
        ],
        "pandas_version":"1.4.0"
    },
    "data":[
        {
            "id":"TRO",
            "nom":"Gabriel",
            "equipe":"Tropics",
            "abbr":"gab",
            "pj":788,
            "b":258,
            "a":457,
            "score":735,
            "massesalariale":88103750
        },
        {
            "id":"PAT",
            "nom":"Hubert",
            "equipe":"Patriotes",
            "abbr":"hub",
            "pj":815,
            "b":244,
            "a":527,
            "score":786,
            "massesalariale":88795095
        },
        {
            "id":"SS",
            "nom":"Rapha\u00ebl",
            "equipe":"Storm Surge",
            "abbr":"rap",
            "pj":746,
            "b":250,
            "a":325,
            "score":616,
            "massesalariale":88216388
        },
        {
            "id":"SLA",
            "nom":"Olivier",
            "equipe":"Slafgoalsky",
            "abbr":"oli",
            "pj":802,
            "b":203,
            "a":318,
            "score":536,
            "massesalariale":71280000
        },
        {
            "id":"QUA",
            "nom":"J\u00e9r\u00e9mieD",
            "equipe":"Qualis",
            "abbr":"jed",
            "pj":663,
            "b":183,
            "a":263,
            "score":459,
            "massesalariale":92840457
        },
        {
            "id":"NOR",
            "nom":"F\u00e9lix-Antoine",
            "equipe":"Nordiques",
            "abbr":"fab",
            "pj":915,
            "b":293,
            "a":453,
            "score":785,
            "massesalariale":102384166
        },
        {
            "id":"VOY",
            "nom":"Nicholas",
            "equipe":"Voyageurs",
            "abbr":"nic",
            "pj":775,
            "b":233,
            "a":374,
            "score":621,
            "massesalariale":86782440
        },
        {
            "id":"JOC",
            "nom":"Lo\u00efc",
            "equipe":"Jockstraps",
            "abbr":"loi",
            "pj":675,
            "b":170,
            "a":203,
            "score":378,
            "massesalariale":81963096
        },
        {
            "id":"TWG",
            "nom":"Dannick",
            "equipe":"Wild Generals",
            "abbr":"dan",
            "pj":686,
            "b":186,
            "a":293,
            "score":493,
            "massesalariale":93761667
        },
        {
            "id":"ROC",
            "nom":"Alexandre",
            "equipe":"Rocket",
            "abbr":"ale",
            "pj":918,
            "b":291,
            "a":395,
            "score":712,
            "massesalariale":93067857
        }
    ]
}